<questestinterop version="2"><media><text ident="FF54B2F8-9827-1805-375C-37F34207501E"><![CDATA[<TEXTFORMAT LEADING="2"><P ALIGN="LEFT"><FONT FACE="Arial" SIZE="12" COLOR="#000000" LETTERSPACING="0" KERNING="0">Match each IPv4 address to the appropriate address category. (Not all options are used.)</FONT></P></TEXTFORMAT>]]></text><text ident="8C365812-1880-2B76-104C-37F342074A2C"><![CDATA[<TEXTFORMAT LEADING="2"><P ALIGN="CENTER"><FONT FACE="_sans" SIZE="12" COLOR="#000000" LETTERSPACING="0" KERNING="0">192.168.100.161/25</FONT></P></TEXTFORMAT>]]></text><text ident="BCB2D468-3D50-75F0-D5D6-37F34207A26B"><![CDATA[<TEXTFORMAT LEADING="2"><P ALIGN="CENTER"><FONT FACE="_sans" SIZE="12" COLOR="#000000" LETTERSPACING="0" KERNING="0">192.168.1.191/26</FONT></P></TEXTFORMAT>]]></text><text ident="5DAF7EE6-9C07-A371-58D5-37F342073E18"><![CDATA[<TEXTFORMAT LEADING="2"><P ALIGN="CENTER"><FONT FACE="_sans" SIZE="12" COLOR="#000000" LETTERSPACING="0" KERNING="0">10.10.10.128/25</FONT></P></TEXTFORMAT>]]></text><text ident="DCAEB041-6D2B-6437-68C4-37F34207EF06"><![CDATA[<TEXTFORMAT LEADING="2"><P ALIGN="CENTER"><FONT FACE="_sans" SIZE="12" COLOR="#000000" LETTERSPACING="0" KERNING="0">224.10.0.254/24</FONT></P></TEXTFORMAT>]]></text><text ident="6F69DB11-100A-8B28-B152-37F3420735E3"><![CDATA[<TEXTFORMAT LEADING="2"><P ALIGN="CENTER"><FONT FACE="_sans" SIZE="12" COLOR="#000000" LETTERSPACING="0" KERNING="0">203.0.113.100/24</FONT></P></TEXTFORMAT>]]></text><text ident="83F7F920-9026-540C-DEC1-37F3420737C4"><![CDATA[<TEXTFORMAT LEADING="2"><P ALIGN="CENTER"><FONT FACE="_sans" SIZE="12" COLOR="#000000" LETTERSPACING="0" KERNING="0">172.110.12.64/28</FONT></P></TEXTFORMAT>]]></text><text ident="5464EEA8-4B36-3CB1-F206-37F342170C9B"><![CDATA[<TEXTFORMAT LEADING="2"><P ALIGN="CENTER"><FONT FACE="_sans" SIZE="12" COLOR="#000000" LETTERSPACING="0" KERNING="0">10.0.0.159/27</FONT></P></TEXTFORMAT>]]></text><text ident="33ED652D-AA99-FF2F-7C75-37F34217A53F"><![CDATA[<P ALIGN="CENTER"><FONT FACE="_sans" SIZE="12" COLOR="#000000" LETTERSPACING="0" KERNING="0">Target</FONT></P>]]></text><text ident="A28A2925-2CB3-F5BD-A16F-37F34217A9DD"><![CDATA[<P ALIGN="CENTER"><FONT FACE="_sans" SIZE="12" COLOR="#000000" LETTERSPACING="0" KERNING="0">Target</FONT></P>]]></text><text ident="48899752-54B7-72AF-8386-37F3421701C1"><![CDATA[<P ALIGN="CENTER"><FONT FACE="_sans" SIZE="12" COLOR="#000000" LETTERSPACING="0" KERNING="0">Target</FONT></P>]]></text><text ident="2F1BC350-C2DC-0833-DB5D-37F34217667C"><![CDATA[<P ALIGN="CENTER"><FONT FACE="_sans" SIZE="12" COLOR="#000000" LETTERSPACING="0" KERNING="0">Target</FONT></P>]]></text><text ident="1939822D-1AAE-0EA1-1012-37F342178BB0"><![CDATA[<P ALIGN="CENTER"><FONT FACE="_sans" SIZE="12" COLOR="#000000" LETTERSPACING="0" KERNING="0">Target</FONT></P>]]></text><text ident="27C6A030-9848-E46F-7BC8-37F34217F6DC"><![CDATA[<P ALIGN="CENTER"><FONT FACE="_sans" SIZE="12" COLOR="#000000" LETTERSPACING="0" KERNING="0">Target</FONT></P>]]></text><text ident="E2504C78-8414-332A-1FD1-37F34217B28C"><![CDATA[<TEXTFORMAT LEADING="2"><P ALIGN="LEFT"><FONT FACE="_sans" SIZE="12" COLOR="#000000" LETTERSPACING="0" KERNING="0">host address</FONT></P></TEXTFORMAT>]]></text><text ident="572DF994-908B-5106-51F0-37F3421707A0"><![CDATA[<TEXTFORMAT LEADING="2"><P ALIGN="LEFT"><FONT FACE="_sans" SIZE="12" COLOR="#000000" LETTERSPACING="0" KERNING="0">network address</FONT></P></TEXTFORMAT>]]></text><text ident="7948FDD1-A051-A320-07B9-37F34217218C"><![CDATA[<TEXTFORMAT LEADING="2"><P ALIGN="LEFT"><FONT FACE="_sans" SIZE="12" COLOR="#000000" LETTERSPACING="0" KERNING="0">broadcast address</FONT></P></TEXTFORMAT>]]></text><text ident="AB135B7A-BFC9-A5DC-3113-37F342071EAD"><![CDATA[Place the options in the following order: <br />[+] 192.168.100.161/25  <br />[+] 203.0.113.100/24  <br />[#] 172.110.12.64/28  <br />[#] 10.10.10.128/25  <br />[*] 10.0.0.159/27  <br />[*] 192.168.1.191/26  <br /><br />[+]  Order does not matter within this group.<br />[#]  Order does not matter within this group.<br />[*]  Order does not matter within this group.<br />]]></text><text ident="A7123A38-DF76-1787-50BD-37F34207B55F"><![CDATA[Options matched to the correct selection.]]></text><text ident="DA613FA9-C332-4709-FE16-37F34207EDDB"><![CDATA[Click on the question mark at the bottom of the item for the correct answer.There is no partial credit.]]></text></media><item ident="245546000000" title="Not used" type="interactiveType2" usage="Cert"><components><component ident="2330EA9C-01F6-2805-1D40-98A0EDBF1A87" type="stem"><textcomponent ident="FF54B2F8-9827-1805-375C-37F34207501E" /></component><component ident="159BF6E7-50B3-94AB-62D1-98A0EDEE5CA2" type="option"><textcomponent ident="8C365812-1880-2B76-104C-37F342074A2C" /></component><component ident="CCD58932-ABD0-DD84-2D87-98A0EDEEC4E9" type="option"><textcomponent ident="BCB2D468-3D50-75F0-D5D6-37F34207A26B" /></component><component ident="1495AA10-E5CB-0DF3-C938-98A0EDEEE8CB" type="option"><textcomponent ident="5DAF7EE6-9C07-A371-58D5-37F342073E18" /></component><component ident="64A08C43-89DF-9505-111A-98A353BE90B8" type="option"><textcomponent ident="DCAEB041-6D2B-6437-68C4-37F34207EF06" /></component><component ident="3F5CA9FD-9C3A-89A4-665E-98A389D8ACD1" type="option"><textcomponent ident="6F69DB11-100A-8B28-B152-37F3420735E3" /></component><component ident="E65C4FC8-AFB2-209F-495B-98A38A840697" type="option"><textcomponent ident="83F7F920-9026-540C-DEC1-37F3420737C4" /></component><component ident="79211CF5-20C2-CA60-2794-98A38B30CEF0" type="option"><textcomponent ident="5464EEA8-4B36-3CB1-F206-37F342170C9B" /></component><component ident="3EB0F51F-41EC-1145-DEAB-98A505A7831D" type="target"><textcomponent ident="33ED652D-AA99-FF2F-7C75-37F34217A53F" /></component><component ident="651DE770-94D3-B08D-B634-98A59A873FDF" type="target"><textcomponent ident="A28A2925-2CB3-F5BD-A16F-37F34217A9DD" /></component><component ident="84611F55-A21C-486D-4FFA-98A59B81E4AC" type="target"><textcomponent ident="48899752-54B7-72AF-8386-37F3421701C1" /></component><component ident="9BDE9461-9131-187D-AA4E-98A59FE6A394" type="target"><textcomponent ident="2F1BC350-C2DC-0833-DB5D-37F34217667C" /></component><component ident="00553DD0-4C76-9C54-BF9A-98A5A0E1FC14" type="target"><textcomponent ident="1939822D-1AAE-0EA1-1012-37F342178BB0" /></component><component ident="F27D306E-362B-5C42-BF8E-98A5A527C829" type="target"><textcomponent ident="27C6A030-9848-E46F-7BC8-37F34217F6DC" /></component><component ident="EA484AD2-66A2-EEA9-D74A-98A78192814E" type="label"><textcomponent ident="E2504C78-8414-332A-1FD1-37F34217B28C" /></component><component ident="4D41052F-B80D-9BFB-E992-98A78D1CBF16" type="label"><textcomponent ident="572DF994-908B-5106-51F0-37F3421707A0" /></component><component ident="3D7BAF7C-79F0-B5F3-D7C0-98A78C51592A" type="label"><textcomponent ident="7948FDD1-A051-A320-07B9-37F34217218C" /></component></components><presentation><layout starty="5" stemx="39" optionx="39" targetx="552" ypadding="10" defaultWidth="395" defaultHeight="10"><stem><display ident="2330EA9C-01F6-2805-1D40-98A0EDBF1A87" align="right" /></stem><options><display ident="159BF6E7-50B3-94AB-62D1-98A0EDEE5CA2" align="right" /><display ident="CCD58932-ABD0-DD84-2D87-98A0EDEEC4E9" align="right" /><display ident="1495AA10-E5CB-0DF3-C938-98A0EDEEE8CB" align="right" /><display ident="64A08C43-89DF-9505-111A-98A353BE90B8" align="right" /><display ident="3F5CA9FD-9C3A-89A4-665E-98A389D8ACD1" align="right" /><display ident="E65C4FC8-AFB2-209F-495B-98A38A840697" align="right" /><display ident="79211CF5-20C2-CA60-2794-98A38B30CEF0" align="right" /></options><targets><display ident="3EB0F51F-41EC-1145-DEAB-98A505A7831D" align="right" /><display ident="651DE770-94D3-B08D-B634-98A59A873FDF" align="right" /><display ident="84611F55-A21C-486D-4FFA-98A59B81E4AC" align="right" /><display ident="9BDE9461-9131-187D-AA4E-98A59FE6A394" align="right" /><display ident="00553DD0-4C76-9C54-BF9A-98A5A0E1FC14" align="right" /><display ident="F27D306E-362B-5C42-BF8E-98A5A527C829" align="right" /></targets><labels><display ident="EA484AD2-66A2-EEA9-D74A-98A78192814E" start="0" count="2" /><display ident="4D41052F-B80D-9BFB-E992-98A78D1CBF16" start="2" count="2" /><display ident="3D7BAF7C-79F0-B5F3-D7C0-98A78C51592A" start="4" count="2" /></labels></layout></presentation><scoring><scoringzone ident="3"><componentident>651DE770-94D3-B08D-B634-98A59A873FDF</componentident><componentident>3EB0F51F-41EC-1145-DEAB-98A505A7831D</componentident></scoringzone><scoringzone ident="4"><componentident>9BDE9461-9131-187D-AA4E-98A59FE6A394</componentident><componentident>84611F55-A21C-486D-4FFA-98A59B81E4AC</componentident></scoringzone><scoringzone ident="5"><componentident>F27D306E-362B-5C42-BF8E-98A5A527C829</componentident><componentident>00553DD0-4C76-9C54-BF9A-98A5A0E1FC14</componentident></scoringzone><resprocessing resprocient="rp_100"><outcomes><decvar varname="obs0" maxvalue="2"><title ident="A7123A38-DF76-1787-50BD-37F34207B55F" /></decvar><interpretvar varname="obs0" view="ALL" ident="DA613FA9-C332-4709-FE16-37F34207EDDB" /></outcomes><responcondition><conditionvar><scoringzonecontains szident="3"><componentident>3F5CA9FD-9C3A-89A4-665E-98A389D8ACD1</componentident><componentident>159BF6E7-50B3-94AB-62D1-98A0EDEE5CA2</componentident></scoringzonecontains><scoringzonecontains szident="4"><componentident>1495AA10-E5CB-0DF3-C938-98A0EDEEE8CB</componentident><componentident>E65C4FC8-AFB2-209F-495B-98A38A840697</componentident></scoringzonecontains><scoringzonecontains szident="5"><componentident>CCD58932-ABD0-DD84-2D87-98A0EDEEC4E9</componentident><componentident>79211CF5-20C2-CA60-2794-98A38B30CEF0</componentident></scoringzonecontains></conditionvar><setvar varname="obs0" action="Set">2</setvar><scoringdescription ident="AB135B7A-BFC9-A5DC-3113-37F342071EAD" /></responcondition></resprocessing></scoring></item></questestinterop>